odoo/addons/base_menu_visibility_restriction/README.rst
odoo/addons/base_menu_visibility_restriction/__init__.py
odoo/addons/base_menu_visibility_restriction/__manifest__.py
odoo/addons/base_menu_visibility_restriction/i18n/base_menu_visibility_restriction.pot
odoo/addons/base_menu_visibility_restriction/i18n/es.po
odoo/addons/base_menu_visibility_restriction/i18n/it.po
odoo/addons/base_menu_visibility_restriction/models/__init__.py
odoo/addons/base_menu_visibility_restriction/models/ir_ui_menu.py
odoo/addons/base_menu_visibility_restriction/readme/CONTRIBUTORS.md
odoo/addons/base_menu_visibility_restriction/readme/DESCRIPTION.md
odoo/addons/base_menu_visibility_restriction/readme/USAGE.md
odoo/addons/base_menu_visibility_restriction/static/description/icon.png
odoo/addons/base_menu_visibility_restriction/static/description/index.html
odoo/addons/base_menu_visibility_restriction/tests/__init__.py
odoo/addons/base_menu_visibility_restriction/tests/test_ir_ui_menu.py
odoo/addons/base_menu_visibility_restriction/views/ir_ui_menu.xml
odoo_addon_base_menu_visibility_restriction-18.0.1.0.0.2.dist-info/METADATA
odoo_addon_base_menu_visibility_restriction-18.0.1.0.0.2.dist-info/WHEEL
odoo_addon_base_menu_visibility_restriction-18.0.1.0.0.2.dist-info/top_level.txt
odoo_addon_base_menu_visibility_restriction-18.0.1.0.0.2.dist-info/RECORD
